c7n_sphinxext/__init__.py
c7n_sphinxext/docgen.py
c7n_sphinxext/_templates/provider-common-elements.rst
c7n_sphinxext/_templates/provider-group.rst
c7n_sphinxext/_templates/provider-index.rst
c7n_sphinxext/_templates/provider-mode.rst
c7n_sphinxext/_templates/provider-resource.rst
c7n_sphinxext/_templates/resource.rst
c7n_sphinxext/_templates/schema.rst
c7n_sphinxext-1.1.48.dist-info/METADATA
c7n_sphinxext-1.1.48.dist-info/WHEEL
c7n_sphinxext-1.1.48.dist-info/entry_points.txt
c7n_sphinxext-1.1.48.dist-info/RECORD
