Metadata-Version: 2.4
Name: c7n_sphinxext
Version: 1.1.48
Summary: Cloud Custodian - Sphinx Extensions
Project-URL: homepage, https://cloudcustodian.io
Project-URL: repository, https://github.com/cloud-custodian/cloud-custodian
Project-URL: documentation, https://cloudcustodian.io/docs
Author: Cloud Custodian Project
License-Expression: Apache-2.0
Classifier: License :: OSI Approved :: Apache Software License
Classifier: Topic :: System :: Distributed Computing
Classifier: Topic :: System :: Systems Administration
Requires-Python: <4.0.0,>=3.9.2
Requires-Dist: c7n ==0.9.49
Requires-Dist: click ==8.3.1
Requires-Dist: myst-parser ==4.0.1
Requires-Dist: pygments ==2.19.2
Requires-Dist: recommonmark ==0.7.1
Requires-Dist: sphinx-markdown-tables ==0.0.17
Requires-Dist: sphinx-rtd-theme ==3.1.0
Requires-Dist: sphinx ==7.4.7
